macpack/__init__.py
macpack/dependency.py
macpack/patcher.py
macpack-1.0.4.dist-info/licenses/LICENSE
macpack-1.0.4.dist-info/METADATA
macpack-1.0.4.dist-info/WHEEL
macpack-1.0.4.dist-info/entry_points.txt
macpack-1.0.4.dist-info/top_level.txt
macpack-1.0.4.dist-info/RECORD
