Metadata-Version: 2.4
Name: macpack
Version: 1.0.4
Summary: Makes a macOS binary redistributable by searching the dependency tree and copying/patching non-system libraries.
Home-page: https://github.com/chearon/macpack
Download-URL: https://github.com/chearon/macpack/tarball/v1.0.4
Author: Caleb Hearon
Author-email: caleb@chearon.net
Keywords: macos,bundle,package,redistribute,redistributable,install_name_tool,otool,mach
License-File: LICENSE
Dynamic: author
Dynamic: author-email
Dynamic: download-url
Dynamic: home-page
Dynamic: keywords
Dynamic: license-file
Dynamic: summary
